unifhycontrib_artemis-0.1.1-py3.8-nspkg.pth
unifhycontrib/artemis/__init__.py
unifhycontrib/artemis/subsurface.py
unifhycontrib/artemis/surfacelayer.py
unifhycontrib/artemis/version.py
unifhycontrib_artemis-0.1.1.dist-info/METADATA
unifhycontrib_artemis-0.1.1.dist-info/WHEEL
unifhycontrib_artemis-0.1.1.dist-info/namespace_packages.txt
unifhycontrib_artemis-0.1.1.dist-info/top_level.txt
unifhycontrib_artemis-0.1.1.dist-info/RECORD
