Metadata-Version: 2.1
Name: unifhycontrib-artemis
Version: 0.1.1
Summary: unifhy components for the Artemis model
Author: Simon J. Dadson, Thibault Hallouin, Rich Ellis
License: BSD-3
Project-URL: Source Code, https://github.com/unifhy-org/unifhycontrib-artemis
Platform: UNKNOWN
Classifier: Development Status :: 4 - Beta
Classifier: Natural Language :: English
Classifier: Topic :: Scientific/Engineering :: Hydrology
Requires-Dist: unifhy (>=0.1.0)
